{"frames": [

{
	"filename": "btnBack.png",
	"frame": {"x":80,"y":61,"w":36,"h":35},
	"rotated": false,
	"trimmed": false,
	"spriteSourceSize": {"x":0,"y":0,"w":36,"h":35},
	"sourceSize": {"w":36,"h":35}
},
{
	"filename": "btnDownload.png",
	"frame": {"x":197,"y":60,"w":41,"h":40},
	"rotated": false,
	"trimmed": false,
	"spriteSourceSize": {"x":0,"y":0,"w":41,"h":40},
	"sourceSize": {"w":41,"h":40}
},
{
	"filename": "btnFullscreenOff.png",
	"frame": {"x":119,"y":61,"w":35,"h":35},
	"rotated": false,
	"trimmed": false,
	"spriteSourceSize": {"x":0,"y":0,"w":35,"h":35},
	"sourceSize": {"w":35,"h":35}
},
{
	"filename": "btnFullscreenOn.png",
	"frame": {"x":4,"y":61,"w":35,"h":36},
	"rotated": false,
	"trimmed": false,
	"spriteSourceSize": {"x":0,"y":0,"w":35,"h":36},
	"sourceSize": {"w":35,"h":36}
},
{
	"filename": "btnHelp.png",
	"frame": {"x":208,"y":103,"w":36,"h":36},
	"rotated": false,
	"trimmed": false,
	"spriteSourceSize": {"x":0,"y":0,"w":36,"h":36},
	"sourceSize": {"w":36,"h":36}
},
{
	"filename": "btnMoreGames.png",
	"frame": {"x":125,"y":103,"w":40,"h":39},
	"rotated": false,
	"trimmed": false,
	"spriteSourceSize": {"x":0,"y":0,"w":40,"h":39},
	"sourceSize": {"w":40,"h":39}
},
{
	"filename": "btnPause.png",
	"frame": {"x":140,"y":145,"w":23,"h":24},
	"rotated": false,
	"trimmed": false,
	"spriteSourceSize": {"x":0,"y":0,"w":23,"h":24},
	"sourceSize": {"w":23,"h":24}
},
{
	"filename": "btnPlay.png",
	"frame": {"x":197,"y":4,"w":53,"h":53},
	"rotated": false,
	"trimmed": false,
	"spriteSourceSize": {"x":0,"y":0,"w":53,"h":53},
	"sourceSize": {"w":53,"h":53}
},
{
	"filename": "btnSettings.png",
	"frame": {"x":42,"y":61,"w":35,"h":36},
	"rotated": false,
	"trimmed": false,
	"spriteSourceSize": {"x":0,"y":0,"w":35,"h":36},
	"sourceSize": {"w":35,"h":36}
},
{
	"filename": "btnSoundOff.png",
	"frame": {"x":168,"y":103,"w":37,"h":36},
	"rotated": false,
	"trimmed": false,
	"spriteSourceSize": {"x":0,"y":0,"w":37,"h":36},
	"sourceSize": {"w":37,"h":36}
},
{
	"filename": "btnSoundOn.png",
	"frame": {"x":157,"y":61,"w":35,"h":35},
	"rotated": false,
	"trimmed": false,
	"spriteSourceSize": {"x":0,"y":0,"w":35,"h":35},
	"sourceSize": {"w":35,"h":35}
},
{
	"filename": "gameover.png",
	"frame": {"x":4,"y":4,"w":190,"h":54},
	"rotated": false,
	"trimmed": false,
	"spriteSourceSize": {"x":0,"y":0,"w":190,"h":54},
	"sourceSize": {"w":190,"h":54}
},
{
	"filename": "kaiStore.png",
	"frame": {"x":4,"y":103,"w":118,"h":43},
	"rotated": false,
	"trimmed": true,
	"spriteSourceSize": {"x":6,"y":6,"w":118,"h":43},
	"sourceSize": {"w":129,"h":55}
},
{
	"filename": "sponsor.png",
	"frame": {"x":4,"y":149,"w":53,"h":11},
	"rotated": false,
	"trimmed": false,
	"spriteSourceSize": {"x":0,"y":0,"w":53,"h":11},
	"sourceSize": {"w":53,"h":11}
},
{
	"filename": "tag#.png",
	"frame": {"x":60,"y":149,"w":17,"h":17},
	"rotated": false,
	"trimmed": false,
	"spriteSourceSize": {"x":0,"y":0,"w":17,"h":17},
	"sourceSize": {"w":17,"h":17}
},
{
	"filename": "tag1.png",
	"frame": {"x":80,"y":149,"w":17,"h":17},
	"rotated": false,
	"trimmed": false,
	"spriteSourceSize": {"x":0,"y":0,"w":17,"h":17},
	"sourceSize": {"w":17,"h":17}
},
{
	"filename": "tag2.png",
	"frame": {"x":100,"y":149,"w":17,"h":17},
	"rotated": false,
	"trimmed": false,
	"spriteSourceSize": {"x":0,"y":0,"w":17,"h":17},
	"sourceSize": {"w":17,"h":17}
},
{
	"filename": "tag3.png",
	"frame": {"x":120,"y":149,"w":17,"h":17},
	"rotated": false,
	"trimmed": false,
	"spriteSourceSize": {"x":0,"y":0,"w":17,"h":17},
	"sourceSize": {"w":17,"h":17}
},
{
	"filename": "tag4.png",
	"frame": {"x":192,"y":142,"w":17,"h":17},
	"rotated": false,
	"trimmed": false,
	"spriteSourceSize": {"x":0,"y":0,"w":17,"h":17},
	"sourceSize": {"w":17,"h":17}
},
{
	"filename": "tag5.png",
	"frame": {"x":212,"y":142,"w":17,"h":17},
	"rotated": false,
	"trimmed": false,
	"spriteSourceSize": {"x":0,"y":0,"w":17,"h":17},
	"sourceSize": {"w":17,"h":17}
},
{
	"filename": "tag8.png",
	"frame": {"x":166,"y":145,"w":23,"h":22},
	"rotated": false,
	"trimmed": false,
	"spriteSourceSize": {"x":0,"y":0,"w":23,"h":22},
	"sourceSize": {"w":23,"h":22}
},
{
	"filename": "tag8_small.png",
	"frame": {"x":232,"y":142,"w":16,"h":15},
	"rotated": false,
	"trimmed": false,
	"spriteSourceSize": {"x":0,"y":0,"w":16,"h":15},
	"sourceSize": {"w":16,"h":15}
}],
"meta": {
	"app": "http://www.codeandweb.com/texturepacker",
	"version": "1.0",
	"image": "spriteAtlas.png",
	"format": "RGBA8888",
	"size": {"w":254,"h":173},
	"scale": "1",
	"smartupdate": "$TexturePacker:SmartUpdate:1454db28f52100d59954e059a1c5229e:9c446066429523a1fcfc1809a4462c43:52d8fd2a569df2ea47da219d52677d60$"
}
}
